reproducible/__init__.py
reproducible/reproducible.py
reproducible-0.4.1.data/data/license.md
reproducible-0.4.1.data/data/readme.md
reproducible-0.4.1.dist-info/METADATA
reproducible-0.4.1.dist-info/WHEEL
reproducible-0.4.1.dist-info/top_level.txt
reproducible-0.4.1.dist-info/RECORD
