Metadata-Version: 2.1
Name: reproducible
Version: 0.4.1
Summary: Reproducible library
Home-page: https://github.com/oist-cnru/reproducible
Author: Fabien C. Y. Benureau
Author-email: fabien@benureau.com
License: BSD
Keywords: replicable reproducible research
Platform: UNKNOWN
Classifier: Development Status :: 4 - Beta
Classifier: Intended Audience :: Science/Research
Classifier: Intended Audience :: Developers
Classifier: Intended Audience :: Education
Classifier: Topic :: Scientific/Engineering
Classifier: Topic :: Software Development :: Testing
Classifier: License :: OSI Approved :: BSD License
Classifier: Programming Language :: Python :: 3
Classifier: Programming Language :: Python :: 3.5
Classifier: Programming Language :: Python :: 3.6
Requires-Dist: gitpython
Requires-Dist: pyyaml
Requires-Dist: py-cpuinfo
Provides-Extra: docs
Requires-Dist: sphinx ; extra == 'docs'
Requires-Dist: sphinx-rtd-theme ; extra == 'docs'
Provides-Extra: tests
Requires-Dist: pytest ; extra == 'tests'
Requires-Dist: pytest-cov ; extra == 'tests'
